npguard/__init__.py
npguard/api.py
npguard/core.py
npguard/log.py
npguard/registry.py
npguard/reporting.py
npguard/static.py
npguard/suggestions.py
npguard/signals/dtype.py
npguard/signals/repetition.py
npguard/signals/temporaries.py
npguard/signals/threading.py
npguard-0.3.1.dist-info/licenses/LICENSE
npguard-0.3.1.dist-info/METADATA
npguard-0.3.1.dist-info/WHEEL
npguard-0.3.1.dist-info/top_level.txt
npguard-0.3.1.dist-info/RECORD
