Metadata-Version: 2.4
Name: npguard
Version: 0.3.1
Summary: NumPy memory observability and explanation tool
Author: Priyanshu Rauth
License: MIT
Project-URL: Homepage, https://github.com/PriyanshuRaut/RNPY
Project-URL: Issues, https://github.com/PriyanshuRaut/RNPY/issues
Keywords: numpy,memory,profiling,performance,scientific-computing,Priyanshu Rauth,npguard,memory management
Classifier: Development Status :: 3 - Alpha
Classifier: Intended Audience :: Developers
Classifier: Topic :: Scientific/Engineering
Classifier: Topic :: Software Development :: Debuggers
Classifier: License :: OSI Approved :: MIT License
Classifier: Programming Language :: Python :: 3
Classifier: Programming Language :: Python :: 3 :: Only
Requires-Python: >=3.8
License-File: LICENSE
Requires-Dist: numpy
Dynamic: license-file
